neo4j_helpers/__init__.py
neo4j_helpers/cypher_dispatcher.py
neo4j_helpers/database_helper.py
neo4j_helpers/local_tools.py
neo4j_helpers/vector_tools.py
neo4j_helpers-0.1.0.dist-info/licenses/LICENSE
neo4j_helpers-0.1.0.dist-info/METADATA
neo4j_helpers-0.1.0.dist-info/WHEEL
neo4j_helpers-0.1.0.dist-info/top_level.txt
neo4j_helpers-0.1.0.dist-info/RECORD
